github_wiki_page_index/__init__.py
github_wiki_page_index/generate_wiki_page_index.py
github_wiki_page_index-0.1.4.dist-info/METADATA
github_wiki_page_index-0.1.4.dist-info/WHEEL
github_wiki_page_index-0.1.4.dist-info/licenses/LICENSE.txt
github_wiki_page_index-0.1.4.dist-info/RECORD
