Metadata-Version: 2.1
Name: github-wiki-page-index
Version: 0.1.4
Summary: Creates an index based on tags for GitHub Wiki pages.
Project-URL: Source code, https://github.com/paulsuh/githubwikipageindex
Author-email: Paul Suh <paul@mspex.net>
License-File: LICENSE.txt
Classifier: Development Status :: 3 - Alpha
Classifier: Intended Audience :: Developers
Classifier: License :: OSI Approved :: BSD License
Classifier: Topic :: Documentation
Classifier: Topic :: Internet :: WWW/HTTP :: Dynamic Content :: Wiki
Classifier: Topic :: Software Development :: Documentation
Requires-Python: >=3.8
Provides-Extra: precommit
Requires-Dist: ruff; extra == 'precommit'
Provides-Extra: unittest
Requires-Dist: pytest; extra == 'unittest'
Requires-Dist: pytest-cov; extra == 'unittest'
